{"cameraMode":{"drawMode":0,"name":"Shaded","section":"Shading Mode"},"sceneLighting":true,"audioPlay":false,"sceneViewState":{"m_AlwaysRefresh":false,"showFog":true,"showSkybox":true,"showFlares":true,"showImageEffects":true,"showParticleSystems":true,"showVisualEffectGraphs":true,"m_FxEnabled":true},"in2DMode":false,"pivot":{"x":-0.07098755240440369,"y":0.5605670213699341,"z":0.48775190114974978},"rotation":{"x":-0.20947793126106263,"y":0.0826072245836258,"z":-0.017763705924153329,"w":-0.9741564989089966},"size":1.0382639169692994,"orthographic":false}